htime/__init__.py
htime/mainparse.py
htime-0.0.4.dist-info/METADATA
htime-0.0.4.dist-info/WHEEL
htime-0.0.4.dist-info/top_level.txt
htime-0.0.4.dist-info/RECORD
