Metadata-Version: 2.1
Name: htime
Version: 0.0.4
Summary: Converting date strings to hammertime strings
Home-page: UNKNOWN
Author: AstroWX
Author-email: <multiidev@gmail.com>
License: UNKNOWN
Keywords: python,discord,hammertime,converter
Platform: UNKNOWN
Classifier: Development Status :: 1 - Planning
Classifier: Intended Audience :: Developers
Classifier: Programming Language :: Python :: 3
Classifier: Operating System :: Unix
Classifier: Operating System :: MacOS :: MacOS X
Classifier: Operating System :: Microsoft :: Windows
Requires-Dist: pytz
Requires-Dist: dateparser
